README.md
setup.py
rnn/__init__.py
rnn.egg-info/PKG-INFO
rnn.egg-info/SOURCES.txt
rnn.egg-info/dependency_links.txt
rnn.egg-info/not-zip-safe
rnn.egg-info/requires.txt
rnn.egg-info/top_level.txt